tcxreader/__init__.py
tcxreader/tcx_author.py
tcxreader/tcx_exercise.py
tcxreader/tcx_lap.py
tcxreader/tcx_track_point.py
tcxreader/tcxreader.py
tcxreader_fork-0.4.10.dist-info/LICENSE
tcxreader_fork-0.4.10.dist-info/METADATA
tcxreader_fork-0.4.10.dist-info/WHEEL
tcxreader_fork-0.4.10.dist-info/top_level.txt
tcxreader_fork-0.4.10.dist-info/RECORD
