Metadata-Version: 2.1
Name: tcxreader_fork
Version: 0.4.10
Summary: tcxreader is a reader for Garmin’s TCX file format. It also works well with missing data! fork from https://github.com/alenrajsp/tcxreader
Home-page: https://github.com/Flavored4179/tcxreader
Author: Alen Rajšp
Author-email: alen.rajsp@gmail.com
Classifier: Programming Language :: Python :: 3.6
Classifier: License :: OSI Approved :: MIT License
Classifier: Operating System :: OS Independent
Classifier: Development Status :: 4 - Beta
Requires-Python: >=3.6
License-File: LICENSE
